mergecraft/__init__.py
mergecraft/mergecraft.py
mergecraft-0.0.10.dist-info/LICENSE
mergecraft-0.0.10.dist-info/METADATA
mergecraft-0.0.10.dist-info/WHEEL
mergecraft-0.0.10.dist-info/entry_points.txt
mergecraft-0.0.10.dist-info/top_level.txt
mergecraft-0.0.10.dist-info/RECORD
