Metadata-Version: 2.1
Name: mergecraft
Version: 0.0.10
Summary: A command-line tool to merge files into a temporary file and open in VS Code. Designed to support AI-driven development.
Home-page: https://github.com/josenerydev/mergecraft
Author: José Nery
Author-email: josenerydev@gmail.com
Classifier: Development Status :: 3 - Alpha
Classifier: Intended Audience :: Developers
Classifier: License :: OSI Approved :: MIT License
Classifier: Programming Language :: Python :: 3
Classifier: Programming Language :: Python :: 3.6
Classifier: Programming Language :: Python :: 3.7
Classifier: Programming Language :: Python :: 3.8
Classifier: Programming Language :: Python :: 3.9
License-File: LICENSE
Requires-Dist: pathspec
Requires-Dist: PyYAML
